<?xml version="1.0" encoding="utf-8"?>
<edmx:Edmx Version="1.0" xmlns:edmx="http://schemas.microsoft.com/ado/2007/06/edmx" xmlns:m="http://schemas.microsoft.com/ado/2007/08/dataservices/metadata" xmlns:sap="http://www.sap.com/Protocols/SAPData">
    <edmx:Reference Uri="http://bgissap1.bgissap.co.kr:8000/sap/opu/odata/iwfnd/catalogservice;v=2/Vocabularies(TechnicalName='%2FIWBEP%2FVOC_AGGREGATION',Version='0001',SAP__Origin='')/$value" xmlns:edmx="http://docs.oasis-open.org/odata/ns/edmx">
        <edmx:Include Namespace="Org.OData.Aggregation.V1" Alias="Aggregation"/>
    </edmx:Reference>
    <edmx:Reference Uri="http://bgissap1.bgissap.co.kr:8000/sap/opu/odata/iwfnd/catalogservice;v=2/Vocabularies(TechnicalName='%2FIWBEP%2FVOC_ANALYTICS',Version='0001',SAP__Origin='')/$value" xmlns:edmx="http://docs.oasis-open.org/odata/ns/edmx">
        <edmx:Include Namespace="com.sap.vocabularies.Analytics.v1" Alias="Analytics"/>
    </edmx:Reference>
    <edmx:Reference Uri="http://bgissap1.bgissap.co.kr:8000/sap/opu/odata/iwfnd/catalogservice;v=2/Vocabularies(TechnicalName='%2FIWBEP%2FVOC_CAPABILITIES',Version='0001',SAP__Origin='')/$value" xmlns:edmx="http://docs.oasis-open.org/odata/ns/edmx">
        <edmx:Include Namespace="Org.OData.Capabilities.V1" Alias="Capabilities"/>
    </edmx:Reference>
    <edmx:Reference Uri="http://bgissap1.bgissap.co.kr:8000/sap/opu/odata/iwfnd/catalogservice;v=2/Vocabularies(TechnicalName='%2FIWBEP%2FVOC_CODELIST',Version='0001',SAP__Origin='')/$value" xmlns:edmx="http://docs.oasis-open.org/odata/ns/edmx">
        <edmx:Include Namespace="com.sap.vocabularies.CodeList.v1" Alias="SAP__CodeList"/>
    </edmx:Reference>
    <edmx:Reference Uri="http://bgissap1.bgissap.co.kr:8000/sap/opu/odata/iwfnd/catalogservice;v=2/Vocabularies(TechnicalName='%2FIWBEP%2FVOC_COMMON',Version='0001',SAP__Origin='')/$value" xmlns:edmx="http://docs.oasis-open.org/odata/ns/edmx">
        <edmx:Include Namespace="com.sap.vocabularies.Common.v1" Alias="Common"/>
        <edmx:Include Namespace="com.sap.vocabularies.Common.v1" Alias="SAP__common"/>
    </edmx:Reference>
    <edmx:Reference Uri="http://bgissap1.bgissap.co.kr:8000/sap/opu/odata/iwfnd/catalogservice;v=2/Vocabularies(TechnicalName='%2FIWBEP%2FVOC_COMMUNICATION',Version='0001',SAP__Origin='')/$value" xmlns:edmx="http://docs.oasis-open.org/odata/ns/edmx">
        <edmx:Include Namespace="com.sap.vocabularies.Communication.v1" Alias="Communication"/>
    </edmx:Reference>
    <edmx:Reference Uri="http://bgissap1.bgissap.co.kr:8000/sap/opu/odata/iwfnd/catalogservice;v=2/Vocabularies(TechnicalName='%2FIWBEP%2FVOC_CORE',Version='0001',SAP__Origin='')/$value" xmlns:edmx="http://docs.oasis-open.org/odata/ns/edmx">
        <edmx:Include Namespace="Org.OData.Core.V1" Alias="SAP__core"/>
    </edmx:Reference>
    <edmx:Reference Uri="http://bgissap1.bgissap.co.kr:8000/sap/opu/odata/iwfnd/catalogservice;v=2/Vocabularies(TechnicalName='%2FIWBEP%2FVOC_MEASURES',Version='0001',SAP__Origin='')/$value" xmlns:edmx="http://docs.oasis-open.org/odata/ns/edmx">
        <edmx:Include Namespace="Org.OData.Measures.V1" Alias="Measures"/>
    </edmx:Reference>
    <edmx:Reference Uri="http://bgissap1.bgissap.co.kr:8000/sap/opu/odata/iwfnd/catalogservice;v=2/Vocabularies(TechnicalName='%2FIWBEP%2FVOC_PDF',Version='0001',SAP__Origin='')/$value" xmlns:edmx="http://docs.oasis-open.org/odata/ns/edmx">
        <edmx:Include Namespace="com.sap.vocabularies.PDF.v1" Alias="SAP__PDF"/>
    </edmx:Reference>
    <edmx:Reference Uri="http://bgissap1.bgissap.co.kr:8000/sap/opu/odata/iwfnd/catalogservice;v=2/Vocabularies(TechnicalName='%2FIWBEP%2FVOC_PERSONALDATA',Version='0001',SAP__Origin='')/$value" xmlns:edmx="http://docs.oasis-open.org/odata/ns/edmx">
        <edmx:Include Namespace="com.sap.vocabularies.PersonalData.v1" Alias="PersonalData"/>
    </edmx:Reference>
    <edmx:Reference Uri="http://bgissap1.bgissap.co.kr:8000/sap/opu/odata/iwfnd/catalogservice;v=2/Vocabularies(TechnicalName='%2FIWBEP%2FVOC_UI',Version='0001',SAP__Origin='')/$value" xmlns:edmx="http://docs.oasis-open.org/odata/ns/edmx">
        <edmx:Include Namespace="com.sap.vocabularies.UI.v1" Alias="UI"/>
    </edmx:Reference>
    <edmx:Reference Uri="http://bgissap1.bgissap.co.kr:8000/sap/opu/odata/iwfnd/catalogservice;v=2/Vocabularies(TechnicalName='%2FIWBEP%2FVOC_VALIDATION',Version='0001',SAP__Origin='')/$value" xmlns:edmx="http://docs.oasis-open.org/odata/ns/edmx">
        <edmx:Include Namespace="Org.OData.Validation.V1" Alias="Validation"/>
    </edmx:Reference>
    <edmx:DataServices m:DataServiceVersion="2.0">
        <Schema Namespace="cds_zc102_p_bp_bp_create_srv" xml:lang="en" sap:schema-version="1" xmlns="http://schemas.microsoft.com/ado/2008/09/edm">
            <EntityType Name="BankSetType" sap:label="[BP] 계좌 생성 Projection view" sap:content-version="1">
                <Key>
                    <PropertyRef Name="Accno"/>
                </Key>
                <Property Name="Accno" Type="Edm.String" Nullable="false" MaxLength="10" sap:display-format="UpperCase" sap:label="계좌코드" sap:updatable="false"/>
                <Property Name="OwnerType" Type="Edm.String" MaxLength="10" sap:display-format="UpperCase" sap:label="소유자 구분"/>
                <Property Name="Partner" Type="Edm.String" MaxLength="12" sap:display-format="UpperCase" sap:label="비즈니스 파트너" sap:updatable="false"/>
                <Property Name="Accnum" Type="Edm.String" MaxLength="22" sap:label="계좌번호"/>
                <Property Name="Bank" Type="Edm.String" MaxLength="2" sap:display-format="UpperCase" sap:label="은행"/>
                <Property Name="Waers" Type="Edm.String" MaxLength="5" sap:display-format="UpperCase" sap:label="통화키" sap:semantics="currency-code"/>
                <NavigationProperty Name="to_BP" Relationship="cds_zc102_p_bp_bp_create_srv.assoc_D64585C2EB8E7EDF8BE3431C99379C6A" FromRole="ToRole_assoc_D64585C2EB8E7EDF8BE3431C99379C6A" ToRole="FromRole_assoc_D64585C2EB8E7EDF8BE3431C99379C6A"/>
            </EntityType>
            <EntityType Name="BpSetType" sap:label="[BP] BP 생성 Projection view" sap:content-version="1">
                <Key>
                    <PropertyRef Name="Partner"/>
                </Key>
                <Property Name="Partner" Type="Edm.String" Nullable="false" MaxLength="12" sap:display-format="UpperCase" sap:label="비즈니스 파트너" sap:updatable="false"/>
                <Property Name="Name1" Type="Edm.String" MaxLength="20" sap:label="비즈니스 파트너 이름"/>
                <Property Name="Venno" Type="Edm.String" MaxLength="10" sap:display-format="UpperCase" sap:label="거래처번호" sap:updatable="false"/>
                <Property Name="Cusno" Type="Edm.String" MaxLength="10" sap:display-format="UpperCase" sap:label="고객 번호" sap:updatable="false"/>
                <Property Name="Accno" Type="Edm.String" MaxLength="10" sap:display-format="UpperCase" sap:label="계좌코드" sap:updatable="false"/>
                <Property Name="BpType" Type="Edm.String" MaxLength="1" sap:display-format="UpperCase" sap:label="BP 타입"/>
                <Property Name="BpRole" Type="Edm.String" MaxLength="1" sap:display-format="UpperCase" sap:label="BP 유형"/>
                <Property Name="BpGroup" Type="Edm.String" MaxLength="10" sap:display-format="UpperCase" sap:label="BP 그룹"/>
                <NavigationProperty Name="to_Bank" Relationship="cds_zc102_p_bp_bp_create_srv.assoc_D64585C2EB8E7EDF8BE3431C99379C6A" FromRole="FromRole_assoc_D64585C2EB8E7EDF8BE3431C99379C6A" ToRole="ToRole_assoc_D64585C2EB8E7EDF8BE3431C99379C6A"/>
                <NavigationProperty Name="to_Credit" Relationship="cds_zc102_p_bp_bp_create_srv.assoc_D3BD57847036AB8ACD9260C169E35821" FromRole="FromRole_assoc_D3BD57847036AB8ACD9260C169E35821" ToRole="ToRole_assoc_D3BD57847036AB8ACD9260C169E35821"/>
                <NavigationProperty Name="to_Customer" Relationship="cds_zc102_p_bp_bp_create_srv.assoc_FAE3ED84C8AAC6AE9251D639C117E8EE" FromRole="FromRole_assoc_FAE3ED84C8AAC6AE9251D639C117E8EE" ToRole="ToRole_assoc_FAE3ED84C8AAC6AE9251D639C117E8EE"/>
                <NavigationProperty Name="to_Vendor" Relationship="cds_zc102_p_bp_bp_create_srv.assoc_B504953806E6704C0E14CFF5538D7C1D" FromRole="FromRole_assoc_B504953806E6704C0E14CFF5538D7C1D" ToRole="ToRole_assoc_B504953806E6704C0E14CFF5538D7C1D"/>
            </EntityType>
            <EntityType Name="CreditSetType" sap:label="[BP] 여신 생성 Projection view" sap:content-version="1">
                <Key>
                    <PropertyRef Name="Partner"/>
                </Key>
                <Property Name="Partner" Type="Edm.String" Nullable="false" MaxLength="12" sap:display-format="UpperCase" sap:label="비즈니스 파트너" sap:creatable="false" sap:updatable="false"/>
                <Property Name="CreditLimit" Type="Edm.Decimal" Precision="13" Scale="3" sap:unit="Waers" sap:variable-scale="true" sap:label="Amount" sap:quickinfo="Amount in document currency"/>
                <Property Name="CreditUsed" Type="Edm.Decimal" Precision="13" Scale="3" sap:unit="Waers" sap:variable-scale="true" sap:label="Amount" sap:quickinfo="Amount in document currency"/>
                <Property Name="Waers" Type="Edm.String" MaxLength="5" sap:display-format="UpperCase" sap:label="Currency" sap:quickinfo="Currency Key" sap:semantics="currency-code"/>
                <Property Name="LastUpdated" Type="Edm.DateTime" Precision="0" sap:display-format="Date" sap:label="Changed On" sap:quickinfo="Last Changed On"/>
                <NavigationProperty Name="to_BP" Relationship="cds_zc102_p_bp_bp_create_srv.assoc_D3BD57847036AB8ACD9260C169E35821" FromRole="ToRole_assoc_D3BD57847036AB8ACD9260C169E35821" ToRole="FromRole_assoc_D3BD57847036AB8ACD9260C169E35821"/>
            </EntityType>
            <EntityType Name="CusSetType" sap:label="[BP] 고객 생성 Projection view" sap:content-version="1">
                <Key>
                    <PropertyRef Name="Cusno"/>
                </Key>
                <Property Name="Cusno" Type="Edm.String" Nullable="false" MaxLength="10" sap:display-format="UpperCase" sap:label="고객 번호" sap:updatable="false"/>
                <Property Name="Partner" Type="Edm.String" MaxLength="12" sap:display-format="UpperCase" sap:label="비즈니스 파트너" sap:updatable="false"/>
                <Property Name="Name1" Type="Edm.String" MaxLength="30" sap:label="고객명"/>
                <Property Name="Telf1" Type="Edm.String" MaxLength="16" sap:label="연락처"/>
                <Property Name="Stras" Type="Edm.String" MaxLength="30" sap:label="주소"/>
                <Property Name="Knkli" Type="Edm.String" MaxLength="10" sap:display-format="UpperCase" sap:label="고객 등급"/>
                <Property Name="Ctlzl" Type="Edm.String" MaxLength="1" sap:display-format="UpperCase" sap:label="신용 평가"/>
                <Property Name="Waers" Type="Edm.String" MaxLength="5" sap:display-format="UpperCase" sap:label="Currency" sap:quickinfo="Currency Key" sap:semantics="currency-code"/>
                <NavigationProperty Name="to_BP" Relationship="cds_zc102_p_bp_bp_create_srv.assoc_FAE3ED84C8AAC6AE9251D639C117E8EE" FromRole="ToRole_assoc_FAE3ED84C8AAC6AE9251D639C117E8EE" ToRole="FromRole_assoc_FAE3ED84C8AAC6AE9251D639C117E8EE"/>
            </EntityType>
            <EntityType Name="VenSetType" sap:label="[BP] 벤더 생성 Projection view" sap:content-version="1">
                <Key>
                    <PropertyRef Name="Venno"/>
                </Key>
                <Property Name="Venno" Type="Edm.String" Nullable="false" MaxLength="10" sap:display-format="UpperCase" sap:label="거래처번호" sap:updatable="false"/>
                <Property Name="Partner" Type="Edm.String" MaxLength="12" sap:display-format="UpperCase" sap:label="비즈니스 파트너" sap:updatable="false"/>
                <Property Name="Name1" Type="Edm.String" MaxLength="20" sap:label="거래처명"/>
                <Property Name="Telf1" Type="Edm.String" MaxLength="20" sap:display-format="NonNegative" sap:label="연락처"/>
                <Property Name="Stras" Type="Edm.String" MaxLength="50" sap:label="주소"/>
                <Property Name="Knkli" Type="Edm.String" MaxLength="2" sap:label="거래처등급"/>
                <NavigationProperty Name="to_BP" Relationship="cds_zc102_p_bp_bp_create_srv.assoc_B504953806E6704C0E14CFF5538D7C1D" FromRole="ToRole_assoc_B504953806E6704C0E14CFF5538D7C1D" ToRole="FromRole_assoc_B504953806E6704C0E14CFF5538D7C1D"/>
            </EntityType>
            <EntityType Name="SAP__Currency" sap:content-version="1">
                <Key>
                    <PropertyRef Name="CurrencyCode"/>
                </Key>
                <Property Name="CurrencyCode" Type="Edm.String" Nullable="false" MaxLength="5" sap:label="Currency" sap:semantics="currency-code"/>
                <Property Name="ISOCode" Type="Edm.String" Nullable="false" MaxLength="3" sap:label="ISO code"/>
                <Property Name="Text" Type="Edm.String" Nullable="false" MaxLength="15" sap:label="Short text"/>
                <Property Name="DecimalPlaces" Type="Edm.Byte" Nullable="false" sap:label="Decimals"/>
            </EntityType>
            <EntityType Name="SAP__UnitOfMeasure" sap:content-version="1">
                <Key>
                    <PropertyRef Name="UnitCode"/>
                </Key>
                <Property Name="UnitCode" Type="Edm.String" Nullable="false" MaxLength="3" sap:label="Internal UoM" sap:semantics="unit-of-measure"/>
                <Property Name="ISOCode" Type="Edm.String" Nullable="false" MaxLength="3" sap:label="ISO Code"/>
                <Property Name="ExternalCode" Type="Edm.String" Nullable="false" MaxLength="3" sap:label="Commercial"/>
                <Property Name="Text" Type="Edm.String" Nullable="false" MaxLength="30" sap:label="Meas. Unit Text"/>
                <Property Name="DecimalPlaces" Type="Edm.Int16" sap:label="Decimal Places"/>
            </EntityType>
            <EntityType Name="SAP__DocumentDescription" sap:content-version="1">
                <Key>
                    <PropertyRef Name="Id"/>
                </Key>
                <Property Name="Id" Type="Edm.Guid" Nullable="false" sap:label="UUID"/>
                <Property Name="CreatedBy" Type="Edm.String" Nullable="false" MaxLength="12"/>
                <Property Name="CreatedAt" Type="Edm.DateTime" Nullable="false" Precision="0" sap:label="Time Stamp"/>
                <Property Name="FileName" Type="Edm.String" Nullable="false" MaxLength="256"/>
                <Property Name="Title" Type="Edm.String" Nullable="false" MaxLength="256"/>
                <NavigationProperty Name="Format" Relationship="cds_zc102_p_bp_bp_create_srv.to_format" FromRole="FromRole_to_format" ToRole="ToRole_to_format"/>
                <NavigationProperty Name="TableColumns" Relationship="cds_zc102_p_bp_bp_create_srv.to_tablecolumns" FromRole="FromRole_to_tablecolumns" ToRole="ToRole_to_tablecolumns"/>
                <NavigationProperty Name="CoverPage" Relationship="cds_zc102_p_bp_bp_create_srv.to_coverpage" FromRole="FromRole_to_coverpage" ToRole="ToRole_to_coverpage"/>
                <NavigationProperty Name="Signature" Relationship="cds_zc102_p_bp_bp_create_srv.to_signature" FromRole="FromRole_to_signature" ToRole="ToRole_to_signature"/>
                <NavigationProperty Name="PDFStandard" Relationship="cds_zc102_p_bp_bp_create_srv.to_pdfstandard" FromRole="FromRole_to_pdfstandard" ToRole="ToRole_to_pdfstandard"/>
                <NavigationProperty Name="Hierarchy" Relationship="cds_zc102_p_bp_bp_create_srv.to_Hierarchy" FromRole="FromRole_to_Hierarchy" ToRole="ToRole_to_Hierarchy"/>
                <NavigationProperty Name="Header" Relationship="cds_zc102_p_bp_bp_create_srv.to_header" FromRole="FromRole_to_header" ToRole="ToRole_to_header"/>
                <NavigationProperty Name="Footer" Relationship="cds_zc102_p_bp_bp_create_srv.to_Footer" FromRole="FromRole_to_Footer" ToRole="ToRole_to_Footer"/>
            </EntityType>
            <EntityType Name="SAP__Format" sap:content-version="1">
                <Key>
                    <PropertyRef Name="Id"/>
                </Key>
                <Property Name="FitToPage" Type="cds_zc102_p_bp_bp_create_srv.SAP__FitToPage" Nullable="false"/>
                <Property Name="Id" Type="Edm.Guid" Nullable="false" sap:label="UUID" sap:creatable="false" sap:updatable="false" sap:sortable="false" sap:filterable="false"/>
                <Property Name="FontSize" Type="Edm.Int32" Nullable="false" sap:creatable="false" sap:updatable="false" sap:sortable="false" sap:filterable="false"/>
                <Property Name="Orientation" Type="Edm.String" Nullable="false" MaxLength="10" sap:creatable="false" sap:updatable="false" sap:sortable="false" sap:filterable="false"/>
                <Property Name="PaperSize" Type="Edm.String" Nullable="false" MaxLength="10" sap:creatable="false" sap:updatable="false" sap:sortable="false" sap:filterable="false"/>
                <Property Name="BorderSize" Type="Edm.Int32" Nullable="false" sap:creatable="false" sap:updatable="false" sap:sortable="false" sap:filterable="false"/>
                <Property Name="MarginSize" Type="Edm.Int32" Nullable="false" sap:creatable="false" sap:updatable="false" sap:sortable="false" sap:filterable="false"/>
                <Property Name="FontName" Type="Edm.String" Nullable="false" MaxLength="255" sap:label="Font Name" sap:creatable="false" sap:updatable="false" sap:sortable="false" sap:filterable="false"/>
                <Property Name="Padding" Type="Edm.Int32" Nullable="false" sap:creatable="false" sap:updatable="false" sap:sortable="false" sap:filterable="false"/>
            </EntityType>
            <EntityType Name="SAP__PDFStandard" sap:content-version="1">
                <Key>
                    <PropertyRef Name="Id"/>
                </Key>
                <Property Name="Id" Type="Edm.Guid" Nullable="false" sap:label="UUID" sap:creatable="false" sap:updatable="false" sap:sortable="false" sap:filterable="false"/>
                <Property Name="UsePDFAConformance" Type="Edm.Boolean" Nullable="false" sap:creatable="false" sap:updatable="false" sap:sortable="false" sap:filterable="false"/>
                <Property Name="DoEnableAccessibility" Type="Edm.Boolean" Nullable="false" sap:label="Indicator" sap:creatable="false" sap:updatable="false" sap:sortable="false" sap:filterable="false"/>
            </EntityType>
            <EntityType Name="SAP__TableColumns" sap:content-version="1">
                <Key>
                    <PropertyRef Name="Id"/>
                    <PropertyRef Name="Name"/>
                    <PropertyRef Name="Header"/>
                </Key>
                <Property Name="Id" Type="Edm.Guid" Nullable="false" sap:label="UUID" sap:creatable="false" sap:updatable="false" sap:sortable="false" sap:filterable="false"/>
                <Property Name="Name" Type="Edm.String" Nullable="false" MaxLength="256" sap:creatable="false" sap:updatable="false" sap:sortable="false" sap:filterable="false"/>
                <Property Name="Header" Type="Edm.String" Nullable="false" MaxLength="256" sap:creatable="false" sap:updatable="false" sap:sortable="false" sap:filterable="false"/>
                <Property Name="HorizontalAlignment" Type="Edm.String" Nullable="false" MaxLength="10" sap:creatable="false" sap:updatable="false" sap:sortable="false" sap:filterable="false"/>
            </EntityType>
            <EntityType Name="SAP__CoverPage" sap:content-version="1">
                <Key>
                    <PropertyRef Name="Title"/>
                    <PropertyRef Name="Id"/>
                    <PropertyRef Name="Name"/>
                </Key>
                <Property Name="Title" Type="Edm.String" Nullable="false" MaxLength="256" sap:creatable="false" sap:updatable="false" sap:sortable="false" sap:filterable="false"/>
                <Property Name="Id" Type="Edm.Guid" Nullable="false" sap:label="UUID" sap:creatable="false" sap:updatable="false" sap:sortable="false" sap:filterable="false"/>
                <Property Name="Name" Type="Edm.String" Nullable="false" MaxLength="256" sap:creatable="false" sap:updatable="false" sap:sortable="false" sap:filterable="false"/>
                <Property Name="Value" Type="Edm.String" Nullable="false" MaxLength="256" sap:creatable="false" sap:updatable="false" sap:sortable="false" sap:filterable="false"/>
            </EntityType>
            <EntityType Name="SAP__Signature" sap:content-version="1">
                <Key>
                    <PropertyRef Name="Id"/>
                </Key>
                <Property Name="Id" Type="Edm.Guid" Nullable="false" sap:label="UUID" sap:creatable="false" sap:updatable="false" sap:sortable="false" sap:filterable="false"/>
                <Property Name="DoSign" Type="Edm.Boolean" Nullable="false" sap:label="Indicator" sap:creatable="false" sap:updatable="false" sap:sortable="false" sap:filterable="false"/>
                <Property Name="Reason" Type="Edm.String" Nullable="false" MaxLength="256" sap:creatable="false" sap:updatable="false" sap:sortable="false" sap:filterable="false"/>
            </EntityType>
            <EntityType Name="SAP__Hierarchy" sap:content-version="1">
                <Key>
                    <PropertyRef Name="Id"/>
                </Key>
                <Property Name="Id" Type="Edm.Guid" Nullable="false" sap:label="UUID" sap:creatable="false" sap:updatable="false" sap:sortable="false" sap:filterable="false"/>
                <Property Name="DistanceFromRootElement" Type="Edm.String" Nullable="false" MaxLength="256" sap:creatable="false" sap:updatable="false" sap:sortable="false" sap:filterable="false"/>
                <Property Name="DrillStateElement" Type="Edm.String" Nullable="false" MaxLength="256" sap:creatable="false" sap:updatable="false" sap:sortable="false" sap:filterable="false"/>
            </EntityType>
            <EntityType Name="SAP__PDFHeader" sap:content-version="1">
                <Key>
                    <PropertyRef Name="Id"/>
                </Key>
                <Property Name="Right" Type="cds_zc102_p_bp_bp_create_srv.SAP__HeaderFooterField" Nullable="false"/>
                <Property Name="Left" Type="cds_zc102_p_bp_bp_create_srv.SAP__HeaderFooterField" Nullable="false"/>
                <Property Name="Center" Type="cds_zc102_p_bp_bp_create_srv.SAP__HeaderFooterField" Nullable="false"/>
                <Property Name="Id" Type="Edm.Guid" Nullable="false" sap:label="UUID" sap:creatable="false" sap:updatable="false" sap:sortable="false" sap:filterable="false"/>
            </EntityType>
            <EntityType Name="SAP__PDFFooter" sap:content-version="1">
                <Key>
                    <PropertyRef Name="Id"/>
                </Key>
                <Property Name="Right" Type="cds_zc102_p_bp_bp_create_srv.SAP__HeaderFooterField" Nullable="false"/>
                <Property Name="Left" Type="cds_zc102_p_bp_bp_create_srv.SAP__HeaderFooterField" Nullable="false"/>
                <Property Name="Center" Type="cds_zc102_p_bp_bp_create_srv.SAP__HeaderFooterField" Nullable="false"/>
                <Property Name="Id" Type="Edm.Guid" Nullable="false" sap:label="UUID" sap:creatable="false" sap:updatable="false" sap:sortable="false" sap:filterable="false"/>
            </EntityType>
            <EntityType Name="SAP__ValueHelp" sap:content-version="1">
                <Key>
                    <PropertyRef Name="VALUEHELP"/>
                </Key>
                <Property Name="VALUEHELP" Type="Edm.String" Nullable="false"/>
                <Property Name="FIELD_VALUE" Type="Edm.String" Nullable="false" MaxLength="10"/>
                <Property Name="DESCRIPTION" Type="Edm.String"/>
            </EntityType>
            <ComplexType Name="SAP__FitToPage">
                <Property Name="ErrorRecoveryBehavior" Type="Edm.String" Nullable="false" MaxLength="8" sap:label="Error behavior" sap:creatable="false" sap:updatable="false" sap:sortable="false" sap:filterable="false"/>
                <Property Name="IsEnabled" Type="Edm.Boolean" Nullable="false" sap:creatable="false" sap:updatable="false" sap:sortable="false" sap:filterable="false"/>
                <Property Name="MinimumFontSize" Type="Edm.Int32" Nullable="false" sap:creatable="false" sap:updatable="false" sap:sortable="false" sap:filterable="false"/>
            </ComplexType>
            <ComplexType Name="SAP__HeaderFooterField">
                <Property Name="Type" Type="Edm.String" Nullable="false" MaxLength="256" sap:creatable="false" sap:updatable="false" sap:sortable="false" sap:filterable="false"/>
            </ComplexType>
            <Association Name="assoc_D3BD57847036AB8ACD9260C169E35821" sap:content-version="1">
                <End Type="cds_zc102_p_bp_bp_create_srv.BpSetType" Multiplicity="1" Role="FromRole_assoc_D3BD57847036AB8ACD9260C169E35821">
                    <OnDelete Action="Cascade"/>
                </End>
                <End Type="cds_zc102_p_bp_bp_create_srv.CreditSetType" Multiplicity="0..1" Role="ToRole_assoc_D3BD57847036AB8ACD9260C169E35821"/>
                <ReferentialConstraint>
                    <Principal Role="FromRole_assoc_D3BD57847036AB8ACD9260C169E35821">
                        <PropertyRef Name="Partner"/>
                    </Principal>
                    <Dependent Role="ToRole_assoc_D3BD57847036AB8ACD9260C169E35821">
                        <PropertyRef Name="Partner"/>
                    </Dependent>
                </ReferentialConstraint>
            </Association>
            <Association Name="assoc_FAE3ED84C8AAC6AE9251D639C117E8EE" sap:content-version="1">
                <End Type="cds_zc102_p_bp_bp_create_srv.BpSetType" Multiplicity="1" Role="FromRole_assoc_FAE3ED84C8AAC6AE9251D639C117E8EE">
                    <OnDelete Action="Cascade"/>
                </End>
                <End Type="cds_zc102_p_bp_bp_create_srv.CusSetType" Multiplicity="0..1" Role="ToRole_assoc_FAE3ED84C8AAC6AE9251D639C117E8EE"/>
                <ReferentialConstraint>
                    <Principal Role="FromRole_assoc_FAE3ED84C8AAC6AE9251D639C117E8EE">
                        <PropertyRef Name="Partner"/>
                    </Principal>
                    <Dependent Role="ToRole_assoc_FAE3ED84C8AAC6AE9251D639C117E8EE">
                        <PropertyRef Name="Partner"/>
                    </Dependent>
                </ReferentialConstraint>
            </Association>
            <Association Name="assoc_B504953806E6704C0E14CFF5538D7C1D" sap:content-version="1">
                <End Type="cds_zc102_p_bp_bp_create_srv.BpSetType" Multiplicity="1" Role="FromRole_assoc_B504953806E6704C0E14CFF5538D7C1D">
                    <OnDelete Action="Cascade"/>
                </End>
                <End Type="cds_zc102_p_bp_bp_create_srv.VenSetType" Multiplicity="0..1" Role="ToRole_assoc_B504953806E6704C0E14CFF5538D7C1D"/>
                <ReferentialConstraint>
                    <Principal Role="FromRole_assoc_B504953806E6704C0E14CFF5538D7C1D">
                        <PropertyRef Name="Partner"/>
                    </Principal>
                    <Dependent Role="ToRole_assoc_B504953806E6704C0E14CFF5538D7C1D">
                        <PropertyRef Name="Partner"/>
                    </Dependent>
                </ReferentialConstraint>
            </Association>
            <Association Name="assoc_D64585C2EB8E7EDF8BE3431C99379C6A" sap:content-version="1">
                <End Type="cds_zc102_p_bp_bp_create_srv.BpSetType" Multiplicity="1" Role="FromRole_assoc_D64585C2EB8E7EDF8BE3431C99379C6A">
                    <OnDelete Action="Cascade"/>
                </End>
                <End Type="cds_zc102_p_bp_bp_create_srv.BankSetType" Multiplicity="*" Role="ToRole_assoc_D64585C2EB8E7EDF8BE3431C99379C6A"/>
                <ReferentialConstraint>
                    <Principal Role="FromRole_assoc_D64585C2EB8E7EDF8BE3431C99379C6A">
                        <PropertyRef Name="Partner"/>
                    </Principal>
                    <Dependent Role="ToRole_assoc_D64585C2EB8E7EDF8BE3431C99379C6A">
                        <PropertyRef Name="Partner"/>
                    </Dependent>
                </ReferentialConstraint>
            </Association>
            <Association Name="to_format" sap:content-version="1">
                <End Type="cds_zc102_p_bp_bp_create_srv.SAP__DocumentDescription" Multiplicity="1" Role="FromRole_to_format"/>
                <End Type="cds_zc102_p_bp_bp_create_srv.SAP__Format" Multiplicity="1" Role="ToRole_to_format"/>
                <ReferentialConstraint>
                    <Principal Role="FromRole_to_format">
                        <PropertyRef Name="Id"/>
                    </Principal>
                    <Dependent Role="ToRole_to_format">
                        <PropertyRef Name="Id"/>
                    </Dependent>
                </ReferentialConstraint>
            </Association>
            <Association Name="to_tablecolumns" sap:content-version="1">
                <End Type="cds_zc102_p_bp_bp_create_srv.SAP__DocumentDescription" Multiplicity="1" Role="FromRole_to_tablecolumns"/>
                <End Type="cds_zc102_p_bp_bp_create_srv.SAP__TableColumns" Multiplicity="*" Role="ToRole_to_tablecolumns"/>
                <ReferentialConstraint>
                    <Principal Role="FromRole_to_tablecolumns">
                        <PropertyRef Name="Id"/>
                    </Principal>
                    <Dependent Role="ToRole_to_tablecolumns">
                        <PropertyRef Name="Id"/>
                    </Dependent>
                </ReferentialConstraint>
            </Association>
            <Association Name="to_coverpage" sap:content-version="1">
                <End Type="cds_zc102_p_bp_bp_create_srv.SAP__DocumentDescription" Multiplicity="1" Role="FromRole_to_coverpage"/>
                <End Type="cds_zc102_p_bp_bp_create_srv.SAP__CoverPage" Multiplicity="*" Role="ToRole_to_coverpage"/>
                <ReferentialConstraint>
                    <Principal Role="FromRole_to_coverpage">
                        <PropertyRef Name="Id"/>
                    </Principal>
                    <Dependent Role="ToRole_to_coverpage">
                        <PropertyRef Name="Id"/>
                    </Dependent>
                </ReferentialConstraint>
            </Association>
            <Association Name="to_signature" sap:content-version="1">
                <End Type="cds_zc102_p_bp_bp_create_srv.SAP__DocumentDescription" Multiplicity="1" Role="FromRole_to_signature"/>
                <End Type="cds_zc102_p_bp_bp_create_srv.SAP__Signature" Multiplicity="1" Role="ToRole_to_signature"/>
                <ReferentialConstraint>
                    <Principal Role="FromRole_to_signature">
                        <PropertyRef Name="Id"/>
                    </Principal>
                    <Dependent Role="ToRole_to_signature">
                        <PropertyRef Name="Id"/>
                    </Dependent>
                </ReferentialConstraint>
            </Association>
            <Association Name="to_pdfstandard" sap:content-version="1">
                <End Type="cds_zc102_p_bp_bp_create_srv.SAP__DocumentDescription" Multiplicity="1" Role="FromRole_to_pdfstandard"/>
                <End Type="cds_zc102_p_bp_bp_create_srv.SAP__PDFStandard" Multiplicity="1" Role="ToRole_to_pdfstandard"/>
                <ReferentialConstraint>
                    <Principal Role="FromRole_to_pdfstandard">
                        <PropertyRef Name="Id"/>
                    </Principal>
                    <Dependent Role="ToRole_to_pdfstandard">
                        <PropertyRef Name="Id"/>
                    </Dependent>
                </ReferentialConstraint>
            </Association>
            <Association Name="to_Hierarchy" sap:content-version="1">
                <End Type="cds_zc102_p_bp_bp_create_srv.SAP__DocumentDescription" Multiplicity="1" Role="FromRole_to_Hierarchy"/>
                <End Type="cds_zc102_p_bp_bp_create_srv.SAP__Hierarchy" Multiplicity="1" Role="ToRole_to_Hierarchy"/>
                <ReferentialConstraint>
                    <Principal Role="FromRole_to_Hierarchy">
                        <PropertyRef Name="Id"/>
                    </Principal>
                    <Dependent Role="ToRole_to_Hierarchy">
                        <PropertyRef Name="Id"/>
                    </Dependent>
                </ReferentialConstraint>
            </Association>
            <Association Name="to_header" sap:content-version="1">
                <End Type="cds_zc102_p_bp_bp_create_srv.SAP__DocumentDescription" Multiplicity="1" Role="FromRole_to_header"/>
                <End Type="cds_zc102_p_bp_bp_create_srv.SAP__PDFHeader" Multiplicity="1" Role="ToRole_to_header"/>
                <ReferentialConstraint>
                    <Principal Role="FromRole_to_header">
                        <PropertyRef Name="Id"/>
                    </Principal>
                    <Dependent Role="ToRole_to_header">
                        <PropertyRef Name="Id"/>
                    </Dependent>
                </ReferentialConstraint>
            </Association>
            <Association Name="to_Footer" sap:content-version="1">
                <End Type="cds_zc102_p_bp_bp_create_srv.SAP__DocumentDescription" Multiplicity="1" Role="FromRole_to_Footer"/>
                <End Type="cds_zc102_p_bp_bp_create_srv.SAP__PDFFooter" Multiplicity="1" Role="ToRole_to_Footer"/>
                <ReferentialConstraint>
                    <Principal Role="FromRole_to_Footer">
                        <PropertyRef Name="Id"/>
                    </Principal>
                    <Dependent Role="ToRole_to_Footer">
                        <PropertyRef Name="Id"/>
                    </Dependent>
                </ReferentialConstraint>
            </Association>
            <EntityContainer Name="cds_zc102_p_bp_bp_create_srv_Entities" m:IsDefaultEntityContainer="true" sap:message-scope-supported="true" sap:supported-formats="atom json xlsx pdf">
                <EntitySet Name="SAP__Currencies" EntityType="cds_zc102_p_bp_bp_create_srv.SAP__Currency" sap:content-version="1"/>
                <EntitySet Name="SAP__UnitsOfMeasure" EntityType="cds_zc102_p_bp_bp_create_srv.SAP__UnitOfMeasure" sap:content-version="1"/>
                <EntitySet Name="SAP__MyDocumentDescriptions" EntityType="cds_zc102_p_bp_bp_create_srv.SAP__DocumentDescription" sap:content-version="1"/>
                <EntitySet Name="SAP__FormatSet" EntityType="cds_zc102_p_bp_bp_create_srv.SAP__Format" sap:creatable="false" sap:updatable="false" sap:deletable="false" sap:pageable="false" sap:addressable="false" sap:content-version="1"/>
                <EntitySet Name="SAP__PDFStandardSet" EntityType="cds_zc102_p_bp_bp_create_srv.SAP__PDFStandard" sap:creatable="false" sap:updatable="false" sap:deletable="false" sap:pageable="false" sap:addressable="false" sap:content-version="1"/>
                <EntitySet Name="SAP__TableColumnsSet" EntityType="cds_zc102_p_bp_bp_create_srv.SAP__TableColumns" sap:creatable="false" sap:updatable="false" sap:deletable="false" sap:pageable="false" sap:addressable="false" sap:content-version="1"/>
                <EntitySet Name="SAP__CoverPageSet" EntityType="cds_zc102_p_bp_bp_create_srv.SAP__CoverPage" sap:creatable="false" sap:updatable="false" sap:deletable="false" sap:pageable="false" sap:addressable="false" sap:content-version="1"/>
                <EntitySet Name="SAP__SignatureSet" EntityType="cds_zc102_p_bp_bp_create_srv.SAP__Signature" sap:creatable="false" sap:updatable="false" sap:deletable="false" sap:pageable="false" sap:addressable="false" sap:content-version="1"/>
                <EntitySet Name="SAP__HierarchySet" EntityType="cds_zc102_p_bp_bp_create_srv.SAP__Hierarchy" sap:creatable="false" sap:updatable="false" sap:deletable="false" sap:pageable="false" sap:addressable="false" sap:content-version="1"/>
                <EntitySet Name="SAP__PDFHeaderSet" EntityType="cds_zc102_p_bp_bp_create_srv.SAP__PDFHeader" sap:creatable="false" sap:updatable="false" sap:deletable="false" sap:pageable="false" sap:addressable="false" sap:content-version="1"/>
                <EntitySet Name="SAP__PDFFooterSet" EntityType="cds_zc102_p_bp_bp_create_srv.SAP__PDFFooter" sap:creatable="false" sap:updatable="false" sap:deletable="false" sap:pageable="false" sap:addressable="false" sap:content-version="1"/>
                <EntitySet Name="SAP__ValueHelpSet" EntityType="cds_zc102_p_bp_bp_create_srv.SAP__ValueHelp" sap:content-version="1"/>
                <EntitySet Name="BankSet" EntityType="cds_zc102_p_bp_bp_create_srv.BankSetType" sap:content-version="1"/>
                <EntitySet Name="BpSet" EntityType="cds_zc102_p_bp_bp_create_srv.BpSetType" sap:content-version="1"/>
                <EntitySet Name="CreditSet" EntityType="cds_zc102_p_bp_bp_create_srv.CreditSetType" sap:content-version="1"/>
                <EntitySet Name="CusSet" EntityType="cds_zc102_p_bp_bp_create_srv.CusSetType" sap:content-version="1"/>
                <EntitySet Name="VenSet" EntityType="cds_zc102_p_bp_bp_create_srv.VenSetType" sap:content-version="1"/>
                <AssociationSet Name="assoc_B504953806E6704C0E14CFF5538D7C1D" Association="cds_zc102_p_bp_bp_create_srv.assoc_B504953806E6704C0E14CFF5538D7C1D" sap:creatable="false" sap:updatable="false" sap:deletable="false" sap:content-version="1">
                    <End EntitySet="BpSet" Role="FromRole_assoc_B504953806E6704C0E14CFF5538D7C1D"/>
                    <End EntitySet="VenSet" Role="ToRole_assoc_B504953806E6704C0E14CFF5538D7C1D"/>
                </AssociationSet>
                <AssociationSet Name="to_FooterSet" Association="cds_zc102_p_bp_bp_create_srv.to_Footer" sap:creatable="false" sap:updatable="false" sap:deletable="false" sap:content-version="1">
                    <End EntitySet="SAP__MyDocumentDescriptions" Role="FromRole_to_Footer"/>
                    <End EntitySet="SAP__PDFFooterSet" Role="ToRole_to_Footer"/>
                </AssociationSet>
                <AssociationSet Name="to_headerSet" Association="cds_zc102_p_bp_bp_create_srv.to_header" sap:creatable="false" sap:updatable="false" sap:deletable="false" sap:content-version="1">
                    <End EntitySet="SAP__MyDocumentDescriptions" Role="FromRole_to_header"/>
                    <End EntitySet="SAP__PDFHeaderSet" Role="ToRole_to_header"/>
                </AssociationSet>
                <AssociationSet Name="assoc_D64585C2EB8E7EDF8BE3431C99379C6A" Association="cds_zc102_p_bp_bp_create_srv.assoc_D64585C2EB8E7EDF8BE3431C99379C6A" sap:creatable="false" sap:updatable="false" sap:deletable="false" sap:content-version="1">
                    <End EntitySet="BpSet" Role="FromRole_assoc_D64585C2EB8E7EDF8BE3431C99379C6A"/>
                    <End EntitySet="BankSet" Role="ToRole_assoc_D64585C2EB8E7EDF8BE3431C99379C6A"/>
                </AssociationSet>
                <AssociationSet Name="to_formatSet" Association="cds_zc102_p_bp_bp_create_srv.to_format" sap:creatable="false" sap:updatable="false" sap:deletable="false" sap:content-version="1">
                    <End EntitySet="SAP__MyDocumentDescriptions" Role="FromRole_to_format"/>
                    <End EntitySet="SAP__FormatSet" Role="ToRole_to_format"/>
                </AssociationSet>
                <AssociationSet Name="to_pdfstandardSet" Association="cds_zc102_p_bp_bp_create_srv.to_pdfstandard" sap:creatable="false" sap:updatable="false" sap:deletable="false" sap:content-version="1">
                    <End EntitySet="SAP__MyDocumentDescriptions" Role="FromRole_to_pdfstandard"/>
                    <End EntitySet="SAP__PDFStandardSet" Role="ToRole_to_pdfstandard"/>
                </AssociationSet>
                <AssociationSet Name="assoc_FAE3ED84C8AAC6AE9251D639C117E8EE" Association="cds_zc102_p_bp_bp_create_srv.assoc_FAE3ED84C8AAC6AE9251D639C117E8EE" sap:creatable="false" sap:updatable="false" sap:deletable="false" sap:content-version="1">
                    <End EntitySet="BpSet" Role="FromRole_assoc_FAE3ED84C8AAC6AE9251D639C117E8EE"/>
                    <End EntitySet="CusSet" Role="ToRole_assoc_FAE3ED84C8AAC6AE9251D639C117E8EE"/>
                </AssociationSet>
                <AssociationSet Name="assoc_D3BD57847036AB8ACD9260C169E35821" Association="cds_zc102_p_bp_bp_create_srv.assoc_D3BD57847036AB8ACD9260C169E35821" sap:creatable="false" sap:updatable="false" sap:deletable="false" sap:content-version="1">
                    <End EntitySet="BpSet" Role="FromRole_assoc_D3BD57847036AB8ACD9260C169E35821"/>
                    <End EntitySet="CreditSet" Role="ToRole_assoc_D3BD57847036AB8ACD9260C169E35821"/>
                </AssociationSet>
                <AssociationSet Name="to_tablecolumnsSet" Association="cds_zc102_p_bp_bp_create_srv.to_tablecolumns" sap:creatable="false" sap:updatable="false" sap:deletable="false" sap:content-version="1">
                    <End EntitySet="SAP__MyDocumentDescriptions" Role="FromRole_to_tablecolumns"/>
                    <End EntitySet="SAP__TableColumnsSet" Role="ToRole_to_tablecolumns"/>
                </AssociationSet>
                <AssociationSet Name="to_signatureSet" Association="cds_zc102_p_bp_bp_create_srv.to_signature" sap:creatable="false" sap:updatable="false" sap:deletable="false" sap:content-version="1">
                    <End EntitySet="SAP__MyDocumentDescriptions" Role="FromRole_to_signature"/>
                    <End EntitySet="SAP__SignatureSet" Role="ToRole_to_signature"/>
                </AssociationSet>
                <AssociationSet Name="to_coverpageSet" Association="cds_zc102_p_bp_bp_create_srv.to_coverpage" sap:creatable="false" sap:updatable="false" sap:deletable="false" sap:content-version="1">
                    <End EntitySet="SAP__MyDocumentDescriptions" Role="FromRole_to_coverpage"/>
                    <End EntitySet="SAP__CoverPageSet" Role="ToRole_to_coverpage"/>
                </AssociationSet>
                <AssociationSet Name="to_HierarchySet" Association="cds_zc102_p_bp_bp_create_srv.to_Hierarchy" sap:creatable="false" sap:updatable="false" sap:deletable="false" sap:content-version="1">
                    <End EntitySet="SAP__MyDocumentDescriptions" Role="FromRole_to_Hierarchy"/>
                    <End EntitySet="SAP__HierarchySet" Role="ToRole_to_Hierarchy"/>
                </AssociationSet>
            </EntityContainer>
            <Annotation Term="Core.SchemaVersion" String="1.0.0" xmlns="http://docs.oasis-open.org/odata/ns/edm"/>
            <Annotations Target="cds_zc102_p_bp_bp_create_srv.cds_zc102_p_bp_bp_create_srv_Entities" xmlns="http://docs.oasis-open.org/odata/ns/edm">
                <Annotation Term="Common.ApplyMultiUnitBehaviorForSortingAndFiltering" Bool="true"/>
            </Annotations>
            <Annotations Target="cds_zc102_p_bp_bp_create_srv.BpSetType/to_Bank" xmlns="http://docs.oasis-open.org/odata/ns/edm">
                <Annotation Term="Common.Composition"/>
            </Annotations>
            <Annotations Target="cds_zc102_p_bp_bp_create_srv.BpSetType/to_Credit" xmlns="http://docs.oasis-open.org/odata/ns/edm">
                <Annotation Term="Common.Composition"/>
            </Annotations>
            <Annotations Target="cds_zc102_p_bp_bp_create_srv.BpSetType/to_Customer" xmlns="http://docs.oasis-open.org/odata/ns/edm">
                <Annotation Term="Common.Composition"/>
            </Annotations>
            <Annotations Target="cds_zc102_p_bp_bp_create_srv.BpSetType/to_Vendor" xmlns="http://docs.oasis-open.org/odata/ns/edm">
                <Annotation Term="Common.Composition"/>
            </Annotations>
            <Annotations Target="cds_zc102_p_bp_bp_create_srv.BankSetType/Accno" xmlns="http://docs.oasis-open.org/odata/ns/edm">
                <Annotation Term="SAP__core.Immutable"/>
            </Annotations>
            <Annotations Target="cds_zc102_p_bp_bp_create_srv.BankSetType/Partner" xmlns="http://docs.oasis-open.org/odata/ns/edm">
                <Annotation Term="SAP__core.Immutable"/>
            </Annotations>
            <Annotations Target="cds_zc102_p_bp_bp_create_srv.BpSetType/Accno" xmlns="http://docs.oasis-open.org/odata/ns/edm">
                <Annotation Term="SAP__core.Immutable"/>
            </Annotations>
            <Annotations Target="cds_zc102_p_bp_bp_create_srv.BpSetType/Cusno" xmlns="http://docs.oasis-open.org/odata/ns/edm">
                <Annotation Term="SAP__core.Immutable"/>
            </Annotations>
            <Annotations Target="cds_zc102_p_bp_bp_create_srv.BpSetType/Partner" xmlns="http://docs.oasis-open.org/odata/ns/edm">
                <Annotation Term="SAP__core.Immutable"/>
            </Annotations>
            <Annotations Target="cds_zc102_p_bp_bp_create_srv.BpSetType/Venno" xmlns="http://docs.oasis-open.org/odata/ns/edm">
                <Annotation Term="SAP__core.Immutable"/>
            </Annotations>
            <Annotations Target="cds_zc102_p_bp_bp_create_srv.CusSetType/Cusno" xmlns="http://docs.oasis-open.org/odata/ns/edm">
                <Annotation Term="SAP__core.Immutable"/>
            </Annotations>
            <Annotations Target="cds_zc102_p_bp_bp_create_srv.CusSetType/Partner" xmlns="http://docs.oasis-open.org/odata/ns/edm">
                <Annotation Term="SAP__core.Immutable"/>
            </Annotations>
            <Annotations Target="cds_zc102_p_bp_bp_create_srv.VenSetType/Partner" xmlns="http://docs.oasis-open.org/odata/ns/edm">
                <Annotation Term="SAP__core.Immutable"/>
            </Annotations>
            <Annotations Target="cds_zc102_p_bp_bp_create_srv.VenSetType/Venno" xmlns="http://docs.oasis-open.org/odata/ns/edm">
                <Annotation Term="SAP__core.Immutable"/>
            </Annotations>
            <Annotations Target="cds_zc102_p_bp_bp_create_srv.cds_zc102_p_bp_bp_create_srv_Entities/BankSet" xmlns="http://docs.oasis-open.org/odata/ns/edm">
                <Annotation Term="Capabilities.NavigationRestrictions">
                    <Record>
                        <PropertyValue Property="RestrictedProperties">
                            <Collection>
                                <Record>
                                    <PropertyValue Property="NavigationProperty" NavigationPropertyPath="to_BP"/>
                                    <PropertyValue Property="InsertRestrictions">
                                        <Record>
                                            <PropertyValue Property="Insertable" Bool="false"/>
                                        </Record>
                                    </PropertyValue>
                                </Record>
                            </Collection>
                        </PropertyValue>
                    </Record>
                </Annotation>
                <Annotation Term="SAP__core.OptimisticConcurrency">
                    <Collection/>
                </Annotation>
            </Annotations>
            <Annotations Target="cds_zc102_p_bp_bp_create_srv.cds_zc102_p_bp_bp_create_srv_Entities/BpSet" xmlns="http://docs.oasis-open.org/odata/ns/edm">
                <Annotation Term="Capabilities.NavigationRestrictions">
                    <Record>
                        <PropertyValue Property="RestrictedProperties">
                            <Collection>
                                <Record>
                                    <PropertyValue Property="NavigationProperty" NavigationPropertyPath="to_Bank"/>
                                    <PropertyValue Property="InsertRestrictions">
                                        <Record>
                                            <PropertyValue Property="Insertable" Bool="true"/>
                                        </Record>
                                    </PropertyValue>
                                </Record>
                                <Record>
                                    <PropertyValue Property="NavigationProperty" NavigationPropertyPath="to_Credit"/>
                                    <PropertyValue Property="InsertRestrictions">
                                        <Record>
                                            <PropertyValue Property="Insertable" Bool="true"/>
                                        </Record>
                                    </PropertyValue>
                                </Record>
                                <Record>
                                    <PropertyValue Property="NavigationProperty" NavigationPropertyPath="to_Customer"/>
                                    <PropertyValue Property="InsertRestrictions">
                                        <Record>
                                            <PropertyValue Property="Insertable" Bool="true"/>
                                        </Record>
                                    </PropertyValue>
                                </Record>
                                <Record>
                                    <PropertyValue Property="NavigationProperty" NavigationPropertyPath="to_Vendor"/>
                                    <PropertyValue Property="InsertRestrictions">
                                        <Record>
                                            <PropertyValue Property="Insertable" Bool="true"/>
                                        </Record>
                                    </PropertyValue>
                                </Record>
                            </Collection>
                        </PropertyValue>
                    </Record>
                </Annotation>
                <Annotation Term="SAP__core.OptimisticConcurrency">
                    <Collection/>
                </Annotation>
            </Annotations>
            <Annotations Target="cds_zc102_p_bp_bp_create_srv.cds_zc102_p_bp_bp_create_srv_Entities/CreditSet" xmlns="http://docs.oasis-open.org/odata/ns/edm">
                <Annotation Term="Capabilities.NavigationRestrictions">
                    <Record>
                        <PropertyValue Property="RestrictedProperties">
                            <Collection>
                                <Record>
                                    <PropertyValue Property="NavigationProperty" NavigationPropertyPath="to_BP"/>
                                    <PropertyValue Property="InsertRestrictions">
                                        <Record>
                                            <PropertyValue Property="Insertable" Bool="false"/>
                                        </Record>
                                    </PropertyValue>
                                </Record>
                            </Collection>
                        </PropertyValue>
                    </Record>
                </Annotation>
                <Annotation Term="SAP__core.OptimisticConcurrency">
                    <Collection/>
                </Annotation>
            </Annotations>
            <Annotations Target="cds_zc102_p_bp_bp_create_srv.cds_zc102_p_bp_bp_create_srv_Entities/CusSet" xmlns="http://docs.oasis-open.org/odata/ns/edm">
                <Annotation Term="Capabilities.NavigationRestrictions">
                    <Record>
                        <PropertyValue Property="RestrictedProperties">
                            <Collection>
                                <Record>
                                    <PropertyValue Property="NavigationProperty" NavigationPropertyPath="to_BP"/>
                                    <PropertyValue Property="InsertRestrictions">
                                        <Record>
                                            <PropertyValue Property="Insertable" Bool="false"/>
                                        </Record>
                                    </PropertyValue>
                                </Record>
                            </Collection>
                        </PropertyValue>
                    </Record>
                </Annotation>
                <Annotation Term="SAP__core.OptimisticConcurrency">
                    <Collection/>
                </Annotation>
            </Annotations>
            <Annotations Target="cds_zc102_p_bp_bp_create_srv.cds_zc102_p_bp_bp_create_srv_Entities/VenSet" xmlns="http://docs.oasis-open.org/odata/ns/edm">
                <Annotation Term="Capabilities.NavigationRestrictions">
                    <Record>
                        <PropertyValue Property="RestrictedProperties">
                            <Collection>
                                <Record>
                                    <PropertyValue Property="NavigationProperty" NavigationPropertyPath="to_BP"/>
                                    <PropertyValue Property="InsertRestrictions">
                                        <Record>
                                            <PropertyValue Property="Insertable" Bool="false"/>
                                        </Record>
                                    </PropertyValue>
                                </Record>
                            </Collection>
                        </PropertyValue>
                    </Record>
                </Annotation>
                <Annotation Term="SAP__core.OptimisticConcurrency">
                    <Collection/>
                </Annotation>
            </Annotations>
            <Annotations Target="cds_zc102_p_bp_bp_create_srv.cds_zc102_p_bp_bp_create_srv_Entities" xmlns="http://docs.oasis-open.org/odata/ns/edm">
                <Annotation Term="Org.OData.Capabilities.V1.BatchSupport">
                    <Record Type="Org.OData.Capabilities.V1.BatchSupportType">
                        <PropertyValue Property="ReferencesAcrossChangeSetsSupported" Bool="true"/>
                    </Record>
                </Annotation>
                <Annotation Term="SAP__CodeList.CurrencyCodes">
                    <Record>
                        <PropertyValue Property="Url" String="./$metadata"/>
                        <PropertyValue Property="CollectionPath" String="SAP__Currencies"/>
                    </Record>
                </Annotation>
                <Annotation Term="SAP__CodeList.UnitsOfMeasure">
                    <Record>
                        <PropertyValue Property="Url" String="./$metadata"/>
                        <PropertyValue Property="CollectionPath" String="SAP__UnitsOfMeasure"/>
                    </Record>
                </Annotation>
                <Annotation Term="SAP__PDF.Features">
                    <Record>
                        <PropertyValue Property="DocumentDescriptionReference" String="./$metadata"/>
                        <PropertyValue Property="DocumentDescriptionCollection" String="SAP__MyDocumentDescriptions"/>
                        <PropertyValue Property="ArchiveFormat" Bool="true"/>
                        <PropertyValue Property="CoverPage" Bool="true"/>
                        <PropertyValue Property="Signature" Bool="true"/>
                        <PropertyValue Property="FitToPage" Bool="true"/>
                        <PropertyValue Property="FontName" Bool="true"/>
                        <PropertyValue Property="FontSize" Bool="true"/>
                        <PropertyValue Property="Margin" Bool="true"/>
                        <PropertyValue Property="Border" Bool="true"/>
                        <PropertyValue Property="Padding" Bool="true"/>
                        <PropertyValue Property="HeaderFooter" Bool="true"/>
                        <PropertyValue Property="ResultSizeDefault" Int="20000"/>
                        <PropertyValue Property="ResultSizeMaximum" Int="20000"/>
                    </Record>
                </Annotation>
                <Annotation Term="SAP__CodeList.SAP__DocumentDescription">
                    <Record>
                        <PropertyValue Property="Url" String="./$metadata"/>
                        <PropertyValue Property="CollectionPath" String="SAP__MyDocumentDescriptions"/>
                    </Record>
                </Annotation>
            </Annotations>
            <Annotations Target="cds_zc102_p_bp_bp_create_srv.SAP__Currency/CurrencyCode" xmlns="http://docs.oasis-open.org/odata/ns/edm">
                <Annotation Term="SAP__common.Text" Path="Text"/>
                <Annotation Term="SAP__common.UnitSpecificScale" Path="DecimalPlaces"/>
                <Annotation Term="SAP__CodeList.StandardCode" Path="ISOCode"/>
            </Annotations>
            <Annotations Target="cds_zc102_p_bp_bp_create_srv.SAP__UnitOfMeasure/UnitCode" xmlns="http://docs.oasis-open.org/odata/ns/edm">
                <Annotation Term="SAP__common.Text" Path="Text"/>
                <Annotation Term="SAP__common.UnitSpecificScale" Path="DecimalPlaces"/>
                <Annotation Term="SAP__CodeList.StandardCode" Path="ISOCode"/>
                <Annotation Term="SAP__CodeList.ExternalCode" Path="ExternalCode"/>
            </Annotations>
            <Annotations Target="cds_zc102_p_bp_bp_create_srv.SAP__UnitOfMeasure" xmlns="http://docs.oasis-open.org/odata/ns/edm">
                <Annotation Term="SAP__core.AlternateKeys">
                    <Collection>
                        <Record>
                            <PropertyValue Property="Key">
                                <Collection>
                                    <Record>
                                        <PropertyValue Property="Name" Path="ExternalCode"/>
                                        <PropertyValue Property="Alias" String="ExternalCode"/>
                                    </Record>
                                </Collection>
                            </PropertyValue>
                        </Record>
                    </Collection>
                </Annotation>
            </Annotations>
            <Annotations Target="cds_zc102_p_bp_bp_create_srv.SAP__DocumentDescription/CreatedBy" xmlns="http://docs.oasis-open.org/odata/ns/edm">
                <Annotation Term="SAP__core.Computed"/>
            </Annotations>
            <Annotations Target="cds_zc102_p_bp_bp_create_srv.SAP__DocumentDescription/CreatedAt" xmlns="http://docs.oasis-open.org/odata/ns/edm">
                <Annotation Term="SAP__core.Computed"/>
            </Annotations>
            <Annotations Target="cds_zc102_p_bp_bp_create_srv.SAP__DocumentDescription" xmlns="http://docs.oasis-open.org/odata/ns/edm">
                <Annotation Term="SAP__capabilties.InsertRestrictions">
                    <Record>
                        <PropertyValue Property="Insertable" Bool="false"/>
                    </Record>
                </Annotation>
                <Annotation Term="SAP__capabilties.UpdateRestrictions">
                    <Record>
                        <PropertyValue Property="Updatable" Bool="false"/>
                        <PropertyValue Property="QueryOptions">
                            <Record>
                                <PropertyValue Property="SelectSupported" Bool="true"/>
                            </Record>
                        </PropertyValue>
                    </Record>
                </Annotation>
                <Annotation Term="SAP__capabilties.DeleteRestrictions">
                    <Record>
                        <PropertyValue Property="Deletable" Bool="false"/>
                    </Record>
                </Annotation>
                <Annotation Term="SAP__capabilties.FilterRestrictions">
                    <Record>
                        <PropertyValue Property="FilterExpressionRestrictions">
                            <Collection>
                                <Record>
                                    <PropertyValue Property="Property" PropertyPath="Format/Orientation"/>
                                    <PropertyValue Property="AllowedExpressions" String="Multivalue"/>
                                </Record>
                                <Record>
                                    <PropertyValue Property="Property" PropertyPath="Format/PaperSize"/>
                                    <PropertyValue Property="AllowedExpressions" String="Multivalue"/>
                                </Record>
                            </Collection>
                        </PropertyValue>
                    </Record>
                </Annotation>
            </Annotations>
            <Annotations Target="cds_zc102_p_bp_bp_create_srv.SAP__Format/FitToPage/ErrorRecoveryBehavior" xmlns="http://docs.oasis-open.org/odata/ns/edm">
                <Annotation Term="SAP__common.ValueListReferences">
                    <Record>
                        <PropertyValue Property="Url" String="./$metadata"/>
                        <PropertyValue Property="CollectionPath" String="../../../../SAP__ValueHelpSet?$filter=VALUEHELP%20eq%20%27ErrorRecoveryBehaviour%27"/>
                    </Record>
                </Annotation>
                <Annotation Term="SAP__common.ValueListWithFixedValues"/>
            </Annotations>
            <Annotations Target="cds_zc102_p_bp_bp_create_srv.SAP__Format/FontName" xmlns="http://docs.oasis-open.org/odata/ns/edm">
                <Annotation Term="SAP__common.ValueListReferences">
                    <Record>
                        <PropertyValue Property="Url" String="./$metadata"/>
                        <PropertyValue Property="CollectionPath" String="SAP__ValueHelpSet?$filter=VALUEHELP%20eq%20%27FontName%27"/>
                    </Record>
                </Annotation>
                <Annotation Term="SAP__common.ValueListWithFixedValues"/>
            </Annotations>
            <Annotations Target="cds_zc102_p_bp_bp_create_srv.SAP__Format/PaperSize" xmlns="http://docs.oasis-open.org/odata/ns/edm">
                <Annotation Term="SAP__common.ValueListReferences">
                    <Record>
                        <PropertyValue Property="Url" String="./$metadata"/>
                        <PropertyValue Property="CollectionPath" String="SAP__ValueHelpSet?$filter=VALUEHELP%20eq%20%27PaperSize%27"/>
                    </Record>
                </Annotation>
                <Annotation Term="SAP__common.ValueListWithFixedValues"/>
            </Annotations>
            <Annotations Target="cds_zc102_p_bp_bp_create_srv.SAP__PDFHeader/Left" xmlns="http://docs.oasis-open.org/odata/ns/edm">
                <Annotation Term="SAP__common.ValueListReferences">
                    <Record>
                        <PropertyValue Property="Url" String="./$metadata"/>
                        <PropertyValue Property="CollectionPath" String="SAP__ValueHelpSet?$filter=VALUEHELP%20eq%20%27HeaderFooter%27"/>
                    </Record>
                </Annotation>
                <Annotation Term="SAP__common.ValueListWithFixedValues"/>
            </Annotations>
            <Annotations Target="cds_zc102_p_bp_bp_create_srv.SAP__PDFHeader/Right" xmlns="http://docs.oasis-open.org/odata/ns/edm">
                <Annotation Term="SAP__common.ValueListReferences">
                    <Record>
                        <PropertyValue Property="Url" String="./$metadata"/>
                        <PropertyValue Property="CollectionPath" String="SAP__ValueHelpSet?$filter=VALUEHELP%20eq%20%27HeaderFooter%27"/>
                    </Record>
                </Annotation>
                <Annotation Term="SAP__common.ValueListWithFixedValues"/>
            </Annotations>
            <Annotations Target="cds_zc102_p_bp_bp_create_srv.SAP__PDFHeader/Center" xmlns="http://docs.oasis-open.org/odata/ns/edm">
                <Annotation Term="SAP__common.ValueListReferences">
                    <Record>
                        <PropertyValue Property="Url" String="./$metadata"/>
                        <PropertyValue Property="CollectionPath" String="SAP__ValueHelpSet?$filter=VALUEHELP%20eq%20%27HeaderFooter%27"/>
                    </Record>
                </Annotation>
                <Annotation Term="SAP__common.ValueListWithFixedValues"/>
            </Annotations>
            <Annotations Target="cds_zc102_p_bp_bp_create_srv.SAP__PDFFooter/Left" xmlns="http://docs.oasis-open.org/odata/ns/edm">
                <Annotation Term="SAP__common.ValueListReferences">
                    <Record>
                        <PropertyValue Property="Url" String="./$metadata"/>
                        <PropertyValue Property="CollectionPath" String="SAP__ValueHelpSet?$filter=VALUEHELP%20eq%20%27HeaderFooter%27"/>
                    </Record>
                </Annotation>
                <Annotation Term="SAP__common.ValueListWithFixedValues"/>
            </Annotations>
            <Annotations Target="cds_zc102_p_bp_bp_create_srv.SAP__PDFFooter/Right" xmlns="http://docs.oasis-open.org/odata/ns/edm">
                <Annotation Term="SAP__common.ValueListReferences">
                    <Record>
                        <PropertyValue Property="Url" String="./$metadata"/>
                        <PropertyValue Property="CollectionPath" String="SAP__ValueHelpSet?$filter=VALUEHELP%20eq%20%27HeaderFooter%27"/>
                    </Record>
                </Annotation>
                <Annotation Term="SAP__common.ValueListWithFixedValues"/>
            </Annotations>
            <Annotations Target="cds_zc102_p_bp_bp_create_srv.SAP__PDFFooter/Center" xmlns="http://docs.oasis-open.org/odata/ns/edm">
                <Annotation Term="SAP__common.ValueListReferences">
                    <Record>
                        <PropertyValue Property="Url" String="./$metadata"/>
                        <PropertyValue Property="CollectionPath" String="SAP__ValueHelpSet?$filter=VALUEHELP%20eq%20%27HeaderFooter%27"/>
                    </Record>
                </Annotation>
                <Annotation Term="SAP__common.ValueListWithFixedValues"/>
            </Annotations>
            <Annotations Target="cds_zc102_p_bp_bp_create_srv.SAP__Format/Orientation" xmlns="http://docs.oasis-open.org/odata/ns/edm">
                <Annotation Term="SAP__common.ValueListReferences">
                    <Record>
                        <PropertyValue Property="Url" String="./$metadata"/>
                        <PropertyValue Property="CollectionPath" String="SAP__ValueHelpSet?$filter=VALUEHELP%20eq%20%27FontName%27"/>
                    </Record>
                </Annotation>
                <Annotation Term="SAP__common.ValueListWithFixedValues"/>
            </Annotations>
            <Annotations Target="cds_zc102_p_bp_bp_create_srv.SAP__TableColumns/HorizontalAlignment" xmlns="http://docs.oasis-open.org/odata/ns/edm">
                <Annotation Term="SAP__common.ValueListReferences">
                    <Record>
                        <PropertyValue Property="Url" String="./$metadata"/>
                        <PropertyValue Property="CollectionPath" String="SAP__ValueHelpSet?$filter=VALUEHELP%20eq%20%27HorizontalAlignment%27"/>
                    </Record>
                </Annotation>
                <Annotation Term="SAP__common.ValueListWithFixedValues"/>
            </Annotations>
            <atom:link rel="self" href="http://bgissap1.bgissap.co.kr:8000/sap/opu/odata/sap/ZC102_P_BP_BP_CREATE_CDS/$metadata" xmlns:atom="http://www.w3.org/2005/Atom"/>
            <atom:link rel="latest-version" href="http://bgissap1.bgissap.co.kr:8000/sap/opu/odata/sap/ZC102_P_BP_BP_CREATE_CDS/$metadata" xmlns:atom="http://www.w3.org/2005/Atom"/>
        </Schema>
    </edmx:DataServices>
</edmx:Edmx>